CHANGES.txt
README.txt
bootstrap.py
buildout.cfg
setup.cfg
setup.py
src/vudo/__init__.py
src/vudo.cmf.egg-info/PKG-INFO
src/vudo.cmf.egg-info/SOURCES.txt
src/vudo.cmf.egg-info/dependency_links.txt
src/vudo.cmf.egg-info/entry_points.txt
src/vudo.cmf.egg-info/namespace_packages.txt
src/vudo.cmf.egg-info/not-zip-safe
src/vudo.cmf.egg-info/requires.txt
src/vudo.cmf.egg-info/top_level.txt
src/vudo/cmf/__init__.py
src/vudo/cmf/actions.py
src/vudo/cmf/api.py
src/vudo/cmf/configure.zcml
src/vudo/cmf/events.py
src/vudo/cmf/form.py
src/vudo/cmf/interfaces.py
src/vudo/cmf/manager.py
src/vudo/cmf/manager.txt
src/vudo/cmf/metadata.py
src/vudo/cmf/model.py
src/vudo/cmf/traversal.py
src/vudo/cmf/utils.py
src/vudo/cmf/views.py
src/vudo/cmf/skin/configure.zcml
src/vudo/cmf/skin/container/configure.zcml
src/vudo/cmf/skin/container/templates/add.pt
src/vudo/cmf/skin/model/configure.zcml
src/vudo/cmf/skin/model/templates/edit.pt
src/vudo/cmf/skin/model/templates/title.pt
src/vudo/cmf/tests/__init__.py
src/vudo/cmf/tests/test_doctests.py